qds_run/__init__.py
qds_run/cli.py
qds_run/config.py
qds_run/constants.py
qds_run/log.py
qds_run/main.py
qds_run/runner.py
qds_run/symbols.py
qds_run-0.1.1.dist-info/entry_points.txt
qds_run-0.1.1.dist-info/LICENSE
qds_run-0.1.1.dist-info/METADATA
qds_run-0.1.1.dist-info/WHEEL
qds_run-0.1.1.dist-info/RECORD
