Metadata-Version: 2.3
Name: qds-run
Version: 0.1.1
Summary: Quick Dirty Scripts
License: MIT
Author: Savio Xavier
Author-email: savioxavier112@gmail.com
Requires-Python: >=3.10,<4.0
Classifier: License :: OSI Approved :: MIT License
Classifier: Programming Language :: Python :: 3
Classifier: Programming Language :: Python :: 3.10
Classifier: Programming Language :: Python :: 3.11
Classifier: Programming Language :: Python :: 3.12
Classifier: Programming Language :: Python :: 3.13
Requires-Dist: cyclopts (>=3.17.0,<4.0.0)
Requires-Dist: inquirerpy (>=0.3.4,<0.4.0)
Requires-Dist: pyboxen (>=1.3.0,<2.0.0)
Requires-Dist: rich (>=14.0.0,<15.0.0)
Requires-Dist: tomlkit (>=0.13.3,<0.14.0)
